{
  "transcript": "-Peppa and George are going inside the boat.",
  "words": [
    {
      "case": "not-found-in-audio",
      "endOffset": 6,
      "startOffset": 1,
      "word": "Peppa"
    },
    {
      "alignedWord": "and",
      "case": "success",
      "end": 0.89,
      "endOffset": 10,
      "phones": [
        {
          "duration": 0.01,
          "phone": "ae_B"
        },
        {
          "duration": 0.05,
          "phone": "n_I"
        },
        {
          "duration": 0.05,
          "phone": "d_E"
        }
      ],
      "start": 0.78,
      "startOffset": 7,
      "word": "and"
    },
    {
      "alignedWord": "george",
      "case": "success",
      "end": 1.29,
      "endOffset": 17,
      "phones": [
        {
          "duration": 0.11,
          "phone": "jh_B"
        },
        {
          "duration": 0.1,
          "phone": "ao_I"
        },
        {
          "duration": 0.05,
          "phone": "r_I"
        },
        {
          "duration": 0.09,
          "phone": "jh_E"
        }
      ],
      "start": 0.94,
      "startOffset": 11,
      "word": "George"
    },
    {
      "alignedWord": "are",
      "case": "success",
      "end": 1.36,
      "endOffset": 21,
      "phones": [
        {
          "duration": 0.01,
          "phone": "aa_B"
        },
        {
          "duration": 0.01,
          "phone": "r_E"
        }
      ],
      "start": 1.34,
      "startOffset": 18,
      "word": "are"
    },
    {
      "alignedWord": "going",
      "case": "success",
      "end": 1.65,
      "endOffset": 27,
      "phones": [
        {
          "duration": 0.07,
          "phone": "g_B"
        },
        {
          "duration": 0.06,
          "phone": "ow_I"
        },
        {
          "duration": 0.08,
          "phone": "ih_I"
        },
        {
          "duration": 0.05,
          "phone": "ng_E"
        }
      ],
      "start": 1.39,
      "startOffset": 22,
      "word": "going"
    },
    {
      "alignedWord": "inside",
      "case": "success",
      "end": 2.05,
      "endOffset": 34,
      "phones": [
        {
          "duration": 0.05,
          "phone": "ih_B"
        },
        {
          "duration": 0.1,
          "phone": "n_I"
        },
        {
          "duration": 0.14,
          "phone": "s_I"
        },
        {
          "duration": 0.09,
          "phone": "ay_I"
        },
        {
          "duration": 0.02,
          "phone": "d_E"
        }
      ],
      "start": 1.65,
      "startOffset": 28,
      "word": "inside"
    },
    {
      "alignedWord": "the",
      "case": "success",
      "end": 2.21,
      "endOffset": 38,
      "phones": [
        {
          "duration": 0.05,
          "phone": "dh_B"
        },
        {
          "duration": 0.08,
          "phone": "ah_E"
        }
      ],
      "start": 2.08,
      "startOffset": 35,
      "word": "the"
    },
    {
      "alignedWord": "boat",
      "case": "success",
      "end": 2.45,
      "endOffset": 43,
      "phones": [
        {
          "duration": 0.01,
          "phone": "b_B"
        },
        {
          "duration": 0.01,
          "phone": "ow_I"
        },
        {
          "duration": 0.01,
          "phone": "t_E"
        }
      ],
      "start": 2.42,
      "startOffset": 39,
      "word": "boat"
    }
  ],
  "speaker": "Narrator",
  "episode_filepath": "data/in/peppa/videos/S02/S02E47 - Captian Daddy Pig.avi",
  "episode_metadata_path": "data/in/peppa/episodes/ep_98.json",
  "episode_title": "Captain Daddy Pig",
  "clipStart": 95,
  "clipEnd": 99,
  "partIndex": 2,
  "clipIndex": 0
}