{
  "transcript": "Zoe Zebra has invited Peppa",
  "words": [
    {
      "alignedWord": "zoe",
      "case": "success",
      "end": 0.8400000000000001,
      "endOffset": 3,
      "phones": [
        {
          "duration": 0.01,
          "phone": "z_B"
        },
        {
          "duration": 0.11,
          "phone": "ow_I"
        },
        {
          "duration": 0.08,
          "phone": "iy_E"
        }
      ],
      "start": 0.64,
      "startOffset": 0,
      "word": "Zoe"
    },
    {
      "alignedWord": "zebra",
      "case": "success",
      "end": 1.16,
      "endOffset": 9,
      "phones": [
        {
          "duration": 0.13,
          "phone": "z_B"
        },
        {
          "duration": 0.01,
          "phone": "iy_I"
        },
        {
          "duration": 0.08,
          "phone": "b_I"
        },
        {
          "duration": 0.03,
          "phone": "r_I"
        },
        {
          "duration": 0.07,
          "phone": "ah_E"
        }
      ],
      "start": 0.84,
      "startOffset": 4,
      "word": "Zebra"
    },
    {
      "alignedWord": "has",
      "case": "success",
      "end": 1.2999999999999998,
      "endOffset": 13,
      "phones": [
        {
          "duration": 0.05,
          "phone": "hh_B"
        },
        {
          "duration": 0.01,
          "phone": "ae_I"
        },
        {
          "duration": 0.06,
          "phone": "z_E"
        }
      ],
      "start": 1.18,
      "startOffset": 10,
      "word": "has"
    },
    {
      "alignedWord": "invited",
      "case": "success",
      "end": 1.7000000000000002,
      "endOffset": 21,
      "phones": [
        {
          "duration": 0.05,
          "phone": "ih_B"
        },
        {
          "duration": 0.09,
          "phone": "n_I"
        },
        {
          "duration": 0.09,
          "phone": "v_I"
        },
        {
          "duration": 0.07,
          "phone": "ay_I"
        },
        {
          "duration": 0.06,
          "phone": "t_I"
        },
        {
          "duration": 0.03,
          "phone": "ah_I"
        },
        {
          "duration": 0.01,
          "phone": "d_E"
        }
      ],
      "start": 1.3,
      "startOffset": 14,
      "word": "invited"
    },
    {
      "alignedWord": "<unk>",
      "case": "success",
      "end": 1.71,
      "endOffset": 27,
      "phones": [
        {
          "duration": 0.01,
          "phone": "oov_S"
        }
      ],
      "start": 1.7,
      "startOffset": 22,
      "word": "Peppa"
    }
  ],
  "speaker": "Narrator",
  "episode_filepath": "data/in/peppa/videos/S02/S02E19 - Zoe Zebra the Postmans Daughter.avi",
  "episode_metadata_path": "data/in/peppa/episodes/ep_80.json",
  "episode_title": "Zoe Zebra the Postman's Daughter",
  "clipStart": 89,
  "clipEnd": 91,
  "partIndex": 3,
  "clipIndex": 0
}