{
  "transcript": "Daddy Pig's favourite room is the museum cafe.",
  "words": [
    {
      "alignedWord": "daddy",
      "case": "success",
      "end": 0.41000000000000003,
      "endOffset": 5,
      "phones": [
        {
          "duration": 0.01,
          "phone": "d_B"
        },
        {
          "duration": 0.07,
          "phone": "ae_I"
        },
        {
          "duration": 0.06,
          "phone": "d_I"
        },
        {
          "duration": 0.08,
          "phone": "iy_E"
        }
      ],
      "start": 0.19,
      "startOffset": 0,
      "word": "Daddy"
    },
    {
      "alignedWord": "pig's",
      "case": "success",
      "end": 0.61,
      "endOffset": 11,
      "phones": [
        {
          "duration": 0.07,
          "phone": "p_B"
        },
        {
          "duration": 0.06,
          "phone": "ih_I"
        },
        {
          "duration": 0.06,
          "phone": "g_I"
        },
        {
          "duration": 0.01,
          "phone": "z_E"
        }
      ],
      "start": 0.41,
      "startOffset": 6,
      "word": "Pig's"
    },
    {
      "alignedWord": "<unk>",
      "case": "success",
      "end": 1.0,
      "endOffset": 21,
      "phones": [
        {
          "duration": 0.39,
          "phone": "oov_S"
        }
      ],
      "start": 0.61,
      "startOffset": 12,
      "word": "favourite"
    },
    {
      "alignedWord": "room",
      "case": "success",
      "end": 1.35,
      "endOffset": 26,
      "phones": [
        {
          "duration": 0.09,
          "phone": "r_B"
        },
        {
          "duration": 0.12,
          "phone": "uw_I"
        },
        {
          "duration": 0.11,
          "phone": "m_E"
        }
      ],
      "start": 1.03,
      "startOffset": 22,
      "word": "room"
    },
    {
      "alignedWord": "is",
      "case": "success",
      "end": 1.9,
      "endOffset": 29,
      "phones": [
        {
          "duration": 0.12,
          "phone": "ih_B"
        },
        {
          "duration": 0.06,
          "phone": "z_E"
        }
      ],
      "start": 1.72,
      "startOffset": 27,
      "word": "is"
    },
    {
      "alignedWord": "the",
      "case": "success",
      "end": 1.99,
      "endOffset": 33,
      "phones": [
        {
          "duration": 0.05,
          "phone": "dh_B"
        },
        {
          "duration": 0.04,
          "phone": "ah_E"
        }
      ],
      "start": 1.9,
      "startOffset": 30,
      "word": "the"
    },
    {
      "alignedWord": "museum",
      "case": "success",
      "end": 2.51,
      "endOffset": 40,
      "phones": [
        {
          "duration": 0.04,
          "phone": "m_B"
        },
        {
          "duration": 0.07,
          "phone": "y_I"
        },
        {
          "duration": 0.08,
          "phone": "uw_I"
        },
        {
          "duration": 0.09,
          "phone": "z_I"
        },
        {
          "duration": 0.09,
          "phone": "iy_I"
        },
        {
          "duration": 0.06,
          "phone": "ah_I"
        },
        {
          "duration": 0.09,
          "phone": "m_E"
        }
      ],
      "start": 1.99,
      "startOffset": 34,
      "word": "museum"
    },
    {
      "alignedWord": "cafe",
      "case": "success",
      "end": 2.9699999999999998,
      "endOffset": 45,
      "phones": [
        {
          "duration": 0.11,
          "phone": "k_B"
        },
        {
          "duration": 0.1,
          "phone": "ae_I"
        },
        {
          "duration": 0.12,
          "phone": "f_I"
        },
        {
          "duration": 0.13,
          "phone": "ey_E"
        }
      ],
      "start": 2.51,
      "startOffset": 41,
      "word": "cafe"
    }
  ],
  "speaker": "Narrator",
  "episode_filepath": "data/in/peppa/videos/S01/S01E30 - The Museum.avi",
  "episode_metadata_path": "data/in/peppa/episodes/ep_39.json",
  "episode_title": "The Museum",
  "clipStart": 269,
  "clipEnd": 273,
  "partIndex": 5,
  "clipIndex": 0
}