{
  "transcript": "So much fruit!",
  "words": [
    {
      "alignedWord": "so",
      "case": "success",
      "end": 2.39,
      "endOffset": 2,
      "phones": [
        {
          "duration": 0.01,
          "phone": "s_B"
        },
        {
          "duration": 0.01,
          "phone": "ow_E"
        }
      ],
      "start": 2.37,
      "startOffset": 0,
      "word": "So"
    },
    {
      "alignedWord": "much",
      "case": "success",
      "end": 2.42,
      "endOffset": 7,
      "phones": [
        {
          "duration": 0.01,
          "phone": "m_B"
        },
        {
          "duration": 0.01,
          "phone": "ah_I"
        },
        {
          "duration": 0.01,
          "phone": "ch_E"
        }
      ],
      "start": 2.39,
      "startOffset": 3,
      "word": "much"
    },
    {
      "case": "not-found-in-audio",
      "endOffset": 13,
      "startOffset": 8,
      "word": "fruit"
    }
  ],
  "speaker": "Peppa",
  "episode_filepath": "data/in/peppa/videos/S05/Fruit.mp4",
  "episode_metadata_path": "data/out/speaker_id/ep_202.yaml",
  "episode_title": "Fruit",
  "clipStart": 48,
  "clipEnd": 51,
  "partIndex": 1,
  "clipIndex": 10
}