{
  "transcript": "Granddad Dog is towing Grandpa Pig's boat home.",
  "words": [
    {
      "alignedWord": "<unk>",
      "case": "success",
      "end": 0.06999999999999999,
      "endOffset": 8,
      "phones": [
        {
          "duration": 0.06,
          "phone": "oov_S"
        }
      ],
      "start": 0.01,
      "startOffset": 0,
      "word": "Granddad"
    },
    {
      "alignedWord": "dog",
      "case": "success",
      "end": 0.1,
      "endOffset": 12,
      "phones": [
        {
          "duration": 0.01,
          "phone": "d_B"
        },
        {
          "duration": 0.01,
          "phone": "ao_I"
        },
        {
          "duration": 0.01,
          "phone": "g_E"
        }
      ],
      "start": 0.07,
      "startOffset": 9,
      "word": "Dog"
    },
    {
      "alignedWord": "is",
      "case": "success",
      "end": 0.16,
      "endOffset": 15,
      "phones": [
        {
          "duration": 0.01,
          "phone": "ih_B"
        },
        {
          "duration": 0.05,
          "phone": "z_E"
        }
      ],
      "start": 0.1,
      "startOffset": 13,
      "word": "is"
    },
    {
      "alignedWord": "towing",
      "case": "success",
      "end": 0.53,
      "endOffset": 22,
      "phones": [
        {
          "duration": 0.09,
          "phone": "t_B"
        },
        {
          "duration": 0.08,
          "phone": "ow_I"
        },
        {
          "duration": 0.06,
          "phone": "ih_I"
        },
        {
          "duration": 0.05,
          "phone": "ng_E"
        }
      ],
      "start": 0.25,
      "startOffset": 16,
      "word": "towing"
    },
    {
      "alignedWord": "grandpa",
      "case": "success",
      "end": 0.95,
      "endOffset": 30,
      "phones": [
        {
          "duration": 0.05,
          "phone": "g_B"
        },
        {
          "duration": 0.07,
          "phone": "r_I"
        },
        {
          "duration": 0.06,
          "phone": "ae_I"
        },
        {
          "duration": 0.06,
          "phone": "m_I"
        },
        {
          "duration": 0.08,
          "phone": "p_I"
        },
        {
          "duration": 0.1,
          "phone": "aa_E"
        }
      ],
      "start": 0.53,
      "startOffset": 23,
      "word": "Grandpa"
    },
    {
      "alignedWord": "pig's",
      "case": "success",
      "end": 1.29,
      "endOffset": 36,
      "phones": [
        {
          "duration": 0.13,
          "phone": "p_B"
        },
        {
          "duration": 0.07,
          "phone": "ih_I"
        },
        {
          "duration": 0.07,
          "phone": "g_I"
        },
        {
          "duration": 0.07,
          "phone": "z_E"
        }
      ],
      "start": 0.95,
      "startOffset": 31,
      "word": "Pig's"
    },
    {
      "alignedWord": "boat",
      "case": "success",
      "end": 1.6,
      "endOffset": 41,
      "phones": [
        {
          "duration": 0.09,
          "phone": "b_B"
        },
        {
          "duration": 0.09,
          "phone": "ow_I"
        },
        {
          "duration": 0.1,
          "phone": "t_E"
        }
      ],
      "start": 1.32,
      "startOffset": 37,
      "word": "boat"
    },
    {
      "alignedWord": "home",
      "case": "success",
      "end": 2.44,
      "endOffset": 46,
      "phones": [
        {
          "duration": 0.01,
          "phone": "hh_B"
        },
        {
          "duration": 0.01,
          "phone": "ow_I"
        },
        {
          "duration": 0.01,
          "phone": "m_E"
        }
      ],
      "start": 2.41,
      "startOffset": 42,
      "word": "home"
    }
  ],
  "speaker": "Narrator",
  "episode_filepath": "data/in/peppa/videos/S01/S01E50 - Grandpa Pig's Boat.avi",
  "episode_metadata_path": "data/in/peppa/episodes/ep_48.json",
  "episode_title": "Grandpa Pig's Boat",
  "clipStart": 265,
  "clipEnd": 268,
  "partIndex": 6,
  "clipIndex": 0
}