{
  "transcript": "This is the picnic area.",
  "words": [
    {
      "alignedWord": "this",
      "case": "success",
      "end": 0.58,
      "endOffset": 4,
      "phones": [
        {
          "duration": 0.15,
          "phone": "dh_B"
        },
        {
          "duration": 0.1,
          "phone": "ih_I"
        },
        {
          "duration": 0.11,
          "phone": "s_E"
        }
      ],
      "start": 0.22,
      "startOffset": 0,
      "word": "This"
    },
    {
      "alignedWord": "is",
      "case": "success",
      "end": 0.76,
      "endOffset": 7,
      "phones": [
        {
          "duration": 0.09,
          "phone": "ih_B"
        },
        {
          "duration": 0.05,
          "phone": "z_E"
        }
      ],
      "start": 0.62,
      "startOffset": 5,
      "word": "is"
    },
    {
      "alignedWord": "the",
      "case": "success",
      "end": 0.88,
      "endOffset": 11,
      "phones": [
        {
          "duration": 0.06,
          "phone": "dh_B"
        },
        {
          "duration": 0.06,
          "phone": "ah_E"
        }
      ],
      "start": 0.76,
      "startOffset": 8,
      "word": "the"
    },
    {
      "alignedWord": "picnic",
      "case": "success",
      "end": 1.32,
      "endOffset": 18,
      "phones": [
        {
          "duration": 0.09,
          "phone": "p_B"
        },
        {
          "duration": 0.08,
          "phone": "ih_I"
        },
        {
          "duration": 0.08,
          "phone": "k_I"
        },
        {
          "duration": 0.04,
          "phone": "n_I"
        },
        {
          "duration": 0.06,
          "phone": "ih_I"
        },
        {
          "duration": 0.09,
          "phone": "k_E"
        }
      ],
      "start": 0.88,
      "startOffset": 12,
      "word": "picnic"
    },
    {
      "alignedWord": "area",
      "case": "success",
      "end": 1.6800000000000002,
      "endOffset": 23,
      "phones": [
        {
          "duration": 0.06,
          "phone": "eh_B"
        },
        {
          "duration": 0.11,
          "phone": "r_I"
        },
        {
          "duration": 0.08,
          "phone": "iy_I"
        },
        {
          "duration": 0.11,
          "phone": "ah_E"
        }
      ],
      "start": 1.32,
      "startOffset": 19,
      "word": "area"
    }
  ],
  "speaker": "Narrator",
  "episode_filepath": "data/in/peppa/videos/S02/S02E02 - Teddys day out.avi",
  "episode_metadata_path": "data/in/peppa/episodes/ep_56.json",
  "episode_title": "Teddy's Day Out",
  "clipStart": 90,
  "clipEnd": 93,
  "partIndex": 2,
  "clipIndex": 0
}