{
  "transcript": "- I hope we get the museum before it closes.",
  "words": [
    {
      "alignedWord": "i",
      "case": "success",
      "end": 1.72,
      "endOffset": 3,
      "phones": [
        {
          "duration": 0.09,
          "phone": "ay_S"
        }
      ],
      "start": 1.63,
      "startOffset": 2,
      "word": "I"
    },
    {
      "alignedWord": "hope",
      "case": "success",
      "end": 1.82,
      "endOffset": 8,
      "phones": [
        {
          "duration": 0.08,
          "phone": "hh_B"
        },
        {
          "duration": 0.01,
          "phone": "ow_I"
        },
        {
          "duration": 0.01,
          "phone": "p_E"
        }
      ],
      "start": 1.72,
      "startOffset": 4,
      "word": "hope"
    },
    {
      "alignedWord": "we",
      "case": "success",
      "end": 2.17,
      "endOffset": 11,
      "phones": [
        {
          "duration": 0.09,
          "phone": "w_B"
        },
        {
          "duration": 0.1,
          "phone": "iy_E"
        }
      ],
      "start": 1.98,
      "startOffset": 9,
      "word": "we"
    },
    {
      "alignedWord": "get",
      "case": "success",
      "end": 2.42,
      "endOffset": 15,
      "phones": [
        {
          "duration": 0.07,
          "phone": "g_B"
        },
        {
          "duration": 0.11,
          "phone": "eh_I"
        },
        {
          "duration": 0.07,
          "phone": "t_E"
        }
      ],
      "start": 2.17,
      "startOffset": 12,
      "word": "get"
    },
    {
      "alignedWord": "the",
      "case": "success",
      "end": 2.6,
      "endOffset": 19,
      "phones": [
        {
          "duration": 0.08,
          "phone": "dh_B"
        },
        {
          "duration": 0.06,
          "phone": "ah_E"
        }
      ],
      "start": 2.46,
      "startOffset": 16,
      "word": "the"
    },
    {
      "alignedWord": "museum",
      "case": "success",
      "end": 3.16,
      "endOffset": 26,
      "phones": [
        {
          "duration": 0.03,
          "phone": "m_B"
        },
        {
          "duration": 0.11,
          "phone": "y_I"
        },
        {
          "duration": 0.1,
          "phone": "uw_I"
        },
        {
          "duration": 0.11,
          "phone": "z_I"
        },
        {
          "duration": 0.14,
          "phone": "iy_I"
        },
        {
          "duration": 0.06,
          "phone": "ah_I"
        },
        {
          "duration": 0.01,
          "phone": "m_E"
        }
      ],
      "start": 2.6,
      "startOffset": 20,
      "word": "museum"
    },
    {
      "alignedWord": "before",
      "case": "success",
      "end": 3.2600000000000002,
      "endOffset": 33,
      "phones": [
        {
          "duration": 0.06,
          "phone": "b_B"
        },
        {
          "duration": 0.01,
          "phone": "ih_I"
        },
        {
          "duration": 0.01,
          "phone": "f_I"
        },
        {
          "duration": 0.01,
          "phone": "ao_I"
        },
        {
          "duration": 0.01,
          "phone": "r_E"
        }
      ],
      "start": 3.16,
      "startOffset": 27,
      "word": "before"
    },
    {
      "alignedWord": "it",
      "case": "success",
      "end": 3.3200000000000003,
      "endOffset": 36,
      "phones": [
        {
          "duration": 0.01,
          "phone": "ih_B"
        },
        {
          "duration": 0.05,
          "phone": "t_E"
        }
      ],
      "start": 3.2600000000000002,
      "startOffset": 34,
      "word": "it"
    },
    {
      "alignedWord": "closes",
      "case": "success",
      "end": 3.52,
      "endOffset": 43,
      "phones": [
        {
          "duration": 0.04,
          "phone": "k_B"
        },
        {
          "duration": 0.07,
          "phone": "l_I"
        },
        {
          "duration": 0.06,
          "phone": "ow_I"
        },
        {
          "duration": 0.01,
          "phone": "z_I"
        },
        {
          "duration": 0.01,
          "phone": "ih_I"
        },
        {
          "duration": 0.01,
          "phone": "z_E"
        }
      ],
      "start": 3.3200000000000003,
      "startOffset": 37,
      "word": "closes"
    }
  ],
  "speaker": "Miss Rabbit",
  "episode_filepath": "data/in/peppa/videos/S05/Pedro is Late.mp4",
  "episode_metadata_path": "data/out/speaker_id/ep_198.yaml",
  "episode_title": "Pedro is Late",
  "clipStart": 150,
  "clipEnd": 154,
  "partIndex": 4,
  "clipIndex": 11
}