{
  "transcript": "Peppa seems to be quite enjoying herself.",
  "words": [
    {
      "alignedWord": "<unk>",
      "case": "success",
      "end": 0.45,
      "endOffset": 5,
      "phones": [
        {
          "duration": 0.13,
          "phone": "oov_S"
        }
      ],
      "start": 0.32,
      "startOffset": 0,
      "word": "Peppa"
    },
    {
      "alignedWord": "seems",
      "case": "success",
      "end": 0.81,
      "endOffset": 11,
      "phones": [
        {
          "duration": 0.15,
          "phone": "s_B"
        },
        {
          "duration": 0.08,
          "phone": "iy_I"
        },
        {
          "duration": 0.07,
          "phone": "m_I"
        },
        {
          "duration": 0.05,
          "phone": "z_E"
        }
      ],
      "start": 0.46,
      "startOffset": 6,
      "word": "seems"
    },
    {
      "alignedWord": "to",
      "case": "success",
      "end": 0.89,
      "endOffset": 14,
      "phones": [
        {
          "duration": 0.05,
          "phone": "t_B"
        },
        {
          "duration": 0.03,
          "phone": "ah_E"
        }
      ],
      "start": 0.81,
      "startOffset": 12,
      "word": "to"
    },
    {
      "alignedWord": "be",
      "case": "success",
      "end": 1.01,
      "endOffset": 17,
      "phones": [
        {
          "duration": 0.06,
          "phone": "b_B"
        },
        {
          "duration": 0.06,
          "phone": "iy_E"
        }
      ],
      "start": 0.89,
      "startOffset": 15,
      "word": "be"
    },
    {
      "alignedWord": "quite",
      "case": "success",
      "end": 1.28,
      "endOffset": 23,
      "phones": [
        {
          "duration": 0.08,
          "phone": "k_B"
        },
        {
          "duration": 0.06,
          "phone": "w_I"
        },
        {
          "duration": 0.06,
          "phone": "ay_I"
        },
        {
          "duration": 0.07,
          "phone": "t_E"
        }
      ],
      "start": 1.01,
      "startOffset": 18,
      "word": "quite"
    },
    {
      "alignedWord": "enjoying",
      "case": "success",
      "end": 1.81,
      "endOffset": 32,
      "phones": [
        {
          "duration": 0.05,
          "phone": "ih_B"
        },
        {
          "duration": 0.11,
          "phone": "n_I"
        },
        {
          "duration": 0.12,
          "phone": "jh_I"
        },
        {
          "duration": 0.07,
          "phone": "oy_I"
        },
        {
          "duration": 0.08,
          "phone": "ih_I"
        },
        {
          "duration": 0.1,
          "phone": "ng_E"
        }
      ],
      "start": 1.28,
      "startOffset": 24,
      "word": "enjoying"
    },
    {
      "alignedWord": "herself",
      "case": "success",
      "end": 2.31,
      "endOffset": 40,
      "phones": [
        {
          "duration": 0.08,
          "phone": "hh_B"
        },
        {
          "duration": 0.02,
          "phone": "er_I"
        },
        {
          "duration": 0.09,
          "phone": "s_I"
        },
        {
          "duration": 0.09,
          "phone": "eh_I"
        },
        {
          "duration": 0.08,
          "phone": "l_I"
        },
        {
          "duration": 0.13,
          "phone": "f_E"
        }
      ],
      "start": 1.82,
      "startOffset": 33,
      "word": "herself"
    }
  ],
  "speaker": "Narrator",
  "episode_filepath": "data/in/peppa/videos/S01/S01E27 - Not Very Well.avi",
  "episode_metadata_path": "data/in/peppa/episodes/ep_25.json",
  "episode_title": "Not Very Well",
  "clipStart": 210,
  "clipEnd": 213,
  "partIndex": 5,
  "clipIndex": 0
}