{
  "transcript": "The puddle is a bit too little for Daddy Pig.",
  "words": [
    {
      "alignedWord": "the",
      "case": "success",
      "end": 0.11,
      "endOffset": 3,
      "phones": [
        {
          "duration": 0.01,
          "phone": "dh_B"
        },
        {
          "duration": 0.01,
          "phone": "ah_E"
        }
      ],
      "start": 0.09,
      "startOffset": 0,
      "word": "The"
    },
    {
      "alignedWord": "puddle",
      "case": "success",
      "end": 0.43,
      "endOffset": 10,
      "phones": [
        {
          "duration": 0.06,
          "phone": "p_B"
        },
        {
          "duration": 0.1,
          "phone": "ah_I"
        },
        {
          "duration": 0.02,
          "phone": "d_I"
        },
        {
          "duration": 0.08,
          "phone": "ah_I"
        },
        {
          "duration": 0.06,
          "phone": "l_E"
        }
      ],
      "start": 0.11,
      "startOffset": 4,
      "word": "puddle"
    },
    {
      "alignedWord": "is",
      "case": "success",
      "end": 0.6,
      "endOffset": 13,
      "phones": [
        {
          "duration": 0.11,
          "phone": "ih_B"
        },
        {
          "duration": 0.06,
          "phone": "z_E"
        }
      ],
      "start": 0.43,
      "startOffset": 11,
      "word": "is"
    },
    {
      "alignedWord": "a",
      "case": "success",
      "end": 0.71,
      "endOffset": 15,
      "phones": [
        {
          "duration": 0.11,
          "phone": "ah_S"
        }
      ],
      "start": 0.6,
      "startOffset": 14,
      "word": "a"
    },
    {
      "alignedWord": "bit",
      "case": "success",
      "end": 1.0,
      "endOffset": 19,
      "phones": [
        {
          "duration": 0.12,
          "phone": "b_B"
        },
        {
          "duration": 0.06,
          "phone": "ih_I"
        },
        {
          "duration": 0.1,
          "phone": "t_E"
        }
      ],
      "start": 0.72,
      "startOffset": 16,
      "word": "bit"
    },
    {
      "alignedWord": "too",
      "case": "success",
      "end": 1.35,
      "endOffset": 23,
      "phones": [
        {
          "duration": 0.12,
          "phone": "t_B"
        },
        {
          "duration": 0.13,
          "phone": "uw_E"
        }
      ],
      "start": 1.1,
      "startOffset": 20,
      "word": "too"
    },
    {
      "alignedWord": "little",
      "case": "success",
      "end": 1.6400000000000001,
      "endOffset": 30,
      "phones": [
        {
          "duration": 0.08,
          "phone": "l_B"
        },
        {
          "duration": 0.05,
          "phone": "ih_I"
        },
        {
          "duration": 0.05,
          "phone": "t_I"
        },
        {
          "duration": 0.05,
          "phone": "ah_I"
        },
        {
          "duration": 0.06,
          "phone": "l_E"
        }
      ],
      "start": 1.35,
      "startOffset": 24,
      "word": "little"
    },
    {
      "alignedWord": "for",
      "case": "success",
      "end": 1.76,
      "endOffset": 34,
      "phones": [
        {
          "duration": 0.06,
          "phone": "f_B"
        },
        {
          "duration": 0.05,
          "phone": "er_E"
        }
      ],
      "start": 1.65,
      "startOffset": 31,
      "word": "for"
    },
    {
      "alignedWord": "daddy",
      "case": "success",
      "end": 2.08,
      "endOffset": 40,
      "phones": [
        {
          "duration": 0.09,
          "phone": "d_B"
        },
        {
          "duration": 0.09,
          "phone": "ae_I"
        },
        {
          "duration": 0.06,
          "phone": "d_I"
        },
        {
          "duration": 0.08,
          "phone": "iy_E"
        }
      ],
      "start": 1.76,
      "startOffset": 35,
      "word": "Daddy"
    },
    {
      "alignedWord": "pig",
      "case": "success",
      "end": 2.39,
      "endOffset": 44,
      "phones": [
        {
          "duration": 0.08,
          "phone": "p_B"
        },
        {
          "duration": 0.1,
          "phone": "ih_I"
        },
        {
          "duration": 0.13,
          "phone": "g_E"
        }
      ],
      "start": 2.08,
      "startOffset": 41,
      "word": "Pig"
    }
  ],
  "speaker": "Narrator",
  "episode_filepath": "data/in/peppa/videos/S02/S02E51 - Daddy Pig's Birthday.avi",
  "episode_metadata_path": "data/in/peppa/episodes/ep_102.json",
  "episode_title": "Daddy Pig's Birthday",
  "clipStart": 237,
  "clipEnd": 240,
  "partIndex": 9,
  "clipIndex": 0
}