{
  "transcript": "And Peppa and George are riding their bicycles.",
  "words": [
    {
      "alignedWord": "and",
      "case": "success",
      "end": 0.42000000000000004,
      "endOffset": 3,
      "phones": [
        {
          "duration": 0.08,
          "phone": "ah_B"
        },
        {
          "duration": 0.07,
          "phone": "n_I"
        },
        {
          "duration": 0.08,
          "phone": "d_E"
        }
      ],
      "start": 0.19,
      "startOffset": 0,
      "word": "And"
    },
    {
      "alignedWord": "<unk>",
      "case": "success",
      "end": 0.77,
      "endOffset": 9,
      "phones": [
        {
          "duration": 0.3,
          "phone": "oov_S"
        }
      ],
      "start": 0.47,
      "startOffset": 4,
      "word": "Peppa"
    },
    {
      "alignedWord": "and",
      "case": "success",
      "end": 0.88,
      "endOffset": 13,
      "phones": [
        {
          "duration": 0.01,
          "phone": "ah_B"
        },
        {
          "duration": 0.01,
          "phone": "n_I"
        },
        {
          "duration": 0.01,
          "phone": "d_E"
        }
      ],
      "start": 0.85,
      "startOffset": 10,
      "word": "and"
    },
    {
      "alignedWord": "george",
      "case": "success",
      "end": 1.23,
      "endOffset": 20,
      "phones": [
        {
          "duration": 0.12,
          "phone": "jh_B"
        },
        {
          "duration": 0.1,
          "phone": "ao_I"
        },
        {
          "duration": 0.01,
          "phone": "r_I"
        },
        {
          "duration": 0.12,
          "phone": "jh_E"
        }
      ],
      "start": 0.88,
      "startOffset": 14,
      "word": "George"
    },
    {
      "alignedWord": "are",
      "case": "success",
      "end": 1.52,
      "endOffset": 24,
      "phones": [
        {
          "duration": 0.01,
          "phone": "er_S"
        }
      ],
      "start": 1.51,
      "startOffset": 21,
      "word": "are"
    },
    {
      "alignedWord": "riding",
      "case": "success",
      "end": 1.87,
      "endOffset": 31,
      "phones": [
        {
          "duration": 0.07,
          "phone": "r_B"
        },
        {
          "duration": 0.1,
          "phone": "ay_I"
        },
        {
          "duration": 0.05,
          "phone": "d_I"
        },
        {
          "duration": 0.06,
          "phone": "ih_I"
        },
        {
          "duration": 0.07,
          "phone": "ng_E"
        }
      ],
      "start": 1.52,
      "startOffset": 25,
      "word": "riding"
    },
    {
      "alignedWord": "their",
      "case": "success",
      "end": 2.0500000000000003,
      "endOffset": 37,
      "phones": [
        {
          "duration": 0.03,
          "phone": "dh_B"
        },
        {
          "duration": 0.07,
          "phone": "eh_I"
        },
        {
          "duration": 0.08,
          "phone": "r_E"
        }
      ],
      "start": 1.87,
      "startOffset": 32,
      "word": "their"
    },
    {
      "alignedWord": "bicycles",
      "case": "success",
      "end": 2.63,
      "endOffset": 46,
      "phones": [
        {
          "duration": 0.1,
          "phone": "b_B"
        },
        {
          "duration": 0.1,
          "phone": "ay_I"
        },
        {
          "duration": 0.06,
          "phone": "s_I"
        },
        {
          "duration": 0.08,
          "phone": "ih_I"
        },
        {
          "duration": 0.03,
          "phone": "k_I"
        },
        {
          "duration": 0.09,
          "phone": "ah_I"
        },
        {
          "duration": 0.1,
          "phone": "l_I"
        },
        {
          "duration": 0.01,
          "phone": "z_E"
        }
      ],
      "start": 2.06,
      "startOffset": 38,
      "word": "bicycles"
    }
  ],
  "speaker": "Narrator",
  "episode_filepath": "data/in/peppa/videos/S01/S01E10 - Bicycles.avi",
  "episode_metadata_path": "data/in/peppa/episodes/ep_12.json",
  "episode_title": "Bicycles",
  "clipStart": 25,
  "clipEnd": 28,
  "partIndex": 0,
  "clipIndex": 1
}