{
  "transcript": "Before going to bed, Peppa",
  "words": [
    {
      "alignedWord": "before",
      "case": "success",
      "end": 2.16,
      "endOffset": 6,
      "phones": [
        {
          "duration": 0.06,
          "phone": "b_B"
        },
        {
          "duration": 0.07,
          "phone": "ih_I"
        },
        {
          "duration": 0.11,
          "phone": "f_I"
        },
        {
          "duration": 0.09,
          "phone": "ao_I"
        },
        {
          "duration": 0.09,
          "phone": "r_E"
        }
      ],
      "start": 1.74,
      "startOffset": 0,
      "word": "Before"
    },
    {
      "alignedWord": "going",
      "case": "success",
      "end": 2.42,
      "endOffset": 12,
      "phones": [
        {
          "duration": 0.07,
          "phone": "g_B"
        },
        {
          "duration": 0.04,
          "phone": "ow_I"
        },
        {
          "duration": 0.07,
          "phone": "ih_I"
        },
        {
          "duration": 0.08,
          "phone": "ng_E"
        }
      ],
      "start": 2.16,
      "startOffset": 7,
      "word": "going"
    },
    {
      "alignedWord": "to",
      "case": "success",
      "end": 2.53,
      "endOffset": 15,
      "phones": [
        {
          "duration": 0.06,
          "phone": "t_B"
        },
        {
          "duration": 0.05,
          "phone": "ah_E"
        }
      ],
      "start": 2.42,
      "startOffset": 13,
      "word": "to"
    },
    {
      "alignedWord": "bed",
      "case": "success",
      "end": 2.6799999999999997,
      "endOffset": 19,
      "phones": [
        {
          "duration": 0.1,
          "phone": "b_B"
        },
        {
          "duration": 0.04,
          "phone": "eh_I"
        },
        {
          "duration": 0.01,
          "phone": "d_E"
        }
      ],
      "start": 2.53,
      "startOffset": 16,
      "word": "bed"
    },
    {
      "alignedWord": "<unk>",
      "case": "success",
      "end": 2.69,
      "endOffset": 26,
      "phones": [
        {
          "duration": 0.01,
          "phone": "oov_S"
        }
      ],
      "start": 2.68,
      "startOffset": 21,
      "word": "Peppa"
    }
  ],
  "speaker": "Narrator",
  "episode_filepath": "data/in/peppa/videos/S01/S01E25 - The Tooth Fairy.avi",
  "episode_metadata_path": "data/in/peppa/episodes/ep_22.json",
  "episode_title": "The Tooth Fairy",
  "clipStart": 121,
  "clipEnd": 124,
  "partIndex": 1,
  "clipIndex": 0
}